iccicd/__init__.py
iccicd/main_cli.py
iccicd/py.typed
iccicd/ci/__init__.py
iccicd/ci/ci.py
iccicd/ci/cli.py
iccicd/packaging/__init__.py
iccicd/packaging/cli.py
iccicd/packaging/python_package.py
iccicd/repo/__init__.py
iccicd/repo/cli.py
iccicd/repo/repo.py
iccicd/repo/python_repo/__init__.py
iccicd/repo/python_repo/pyproject.py
iccicd/repo/python_repo/python_repo.py
iccicd/repo/python_repo/sphinx.py
iccicd/version_control/__init__.py
iccicd/version_control/merge_request.py
iccicd-0.1.6.dist-info/licenses/LICENSE.txt
iccicd-0.1.6.dist-info/METADATA
iccicd-0.1.6.dist-info/WHEEL
iccicd-0.1.6.dist-info/entry_points.txt
iccicd-0.1.6.dist-info/top_level.txt
iccicd-0.1.6.dist-info/RECORD
