Metadata-Version: 2.4
Name: iccicd
Version: 0.1.6
Summary: A collection of utilities to manage ICHEC project CI/CD pipelines.
Author-email: "James Grogan, Irish Centre for High End Computing" <james.grogan@ichec.ie>
Project-URL: Repository, https://git.ichec.ie/performance/toolshed/iccicd
Project-URL: Homepage, https://git.ichec.ie/performance/toolshed/iccicd
Keywords: CICD,HPC,Gitlab
Classifier: Development Status :: 3 - Alpha
Classifier: Programming Language :: Python :: 3
Classifier: License :: OSI Approved :: GNU General Public License v3 or later (GPLv3+)
Classifier: Operating System :: OS Independent
Classifier: Topic :: System :: Distributed Computing
Requires-Python: >=3.10
License-File: LICENSE.txt
Requires-Dist: build
Requires-Dist: twine
Requires-Dist: iccore==0.1.11
Requires-Dist: tomlkit
Provides-Extra: test
Requires-Dist: pytest; extra == "test"
Requires-Dist: pytest-cov; extra == "test"
Requires-Dist: pytest-sugar; extra == "test"
Requires-Dist: black; extra == "test"
Requires-Dist: mypy; extra == "test"
Requires-Dist: flake8; extra == "test"
Requires-Dist: pylint; extra == "test"
Dynamic: license-file
